client/__init__.py
client/client.py
grpcDir/__init__.py
grpcDir/file_pb2.py
grpcDir/file_pb2_grpc.py
grpcDir/lodger_pb2.py
grpcDir/lodger_pb2_grpc.py
tensornlp/__init__.py
tensornlp/client/__init__.py
tensornlp/client/client.py
tensornlp/grpcDir/__init__.py
tensornlp/grpcDir/file_pb2.py
tensornlp/grpcDir/file_pb2_grpc.py
tensornlp/grpcDir/lodger_pb2.py
tensornlp/grpcDir/lodger_pb2_grpc.py
Tensornlp-0.5.1.dist-info/METADATA
Tensornlp-0.5.1.dist-info/WHEEL
Tensornlp-0.5.1.dist-info/top_level.txt
Tensornlp-0.5.1.dist-info/RECORD
