Metadata-Version: 2.1
Name: Tensornlp
Version: 0.5.1
Summary: A tensornlp library for NLP tasks
Author: Hamza Khan
Author-email: hamzamania@gmail.com
Classifier: Programming Language :: Python :: 3
Classifier: License :: OSI Approved :: MIT License
Classifier: Operating System :: OS Independent
Requires-Python: >=3.6
Requires-Dist: grpcio
Requires-Dist: grpcio-tools
Requires-Dist: protobuf
Requires-Dist: pymongo
